Metadata-Version: 2.1
Name: pygrocy-ext
Version: 1.0.10
Summary: UNKNOWN
Home-page: UNKNOWN
License: MIT
Platform: UNKNOWN
Classifier: Programming Language :: Python :: 3
Classifier: License :: OSI Approved :: MIT License
Classifier: Operating System :: OS Independent
License-File: LICENSE
Requires-Dist: requests
Requires-Dist: iso8601 (~=0.1.16)
Requires-Dist: pytz (~=2021.1)
Requires-Dist: tzlocal (<3.0,>=2.1)
Requires-Dist: deprecation (~=2.1.0)
